README.rst
setup.py
scikit_neuralnetwork.egg-info/PKG-INFO
scikit_neuralnetwork.egg-info/SOURCES.txt
scikit_neuralnetwork.egg-info/dependency_links.txt
scikit_neuralnetwork.egg-info/not-zip-safe
scikit_neuralnetwork.egg-info/requires.txt
scikit_neuralnetwork.egg-info/top_level.txt
sknn/__init__.py
sknn/ae.py
sknn/mlp.py
sknn/nn.py
sknn/backend/__init__.py
sknn/backend/base.py
sknn/backend/lasagne/__init__.py
sknn/backend/lasagne/mlp.py
sknn/tests/__init__.py
sknn/tests/test_ae.py
sknn/tests/test_callback.py
sknn/tests/test_classifier.py
sknn/tests/test_conv.py
sknn/tests/test_data.py
sknn/tests/test_deep.py
sknn/tests/test_layers.py
sknn/tests/test_linear.py
sknn/tests/test_nn.py
sknn/tests/test_output.py
sknn/tests/test_pipeline.py
sknn/tests/test_platform.py
sknn/tests/test_rules.py
sknn/tests/test_sklearn.py
sknn/tests/test_training.py
sknn/tests/test_types.py